.gitignore
MANIFEST.in
Makefile
README.md
requirements.txt
setup.py
.github/workflows/pythonpackage.yml
elpulga/__init__.py
elpulga/lib.py
elpulga.egg-info/PKG-INFO
elpulga.egg-info/SOURCES.txt
elpulga.egg-info/dependency_links.txt
elpulga.egg-info/not-zip-safe
elpulga.egg-info/requires.txt
elpulga.egg-info/top_level.txt
elpulga/data/.keep
notebooks/.keep
scripts/elpulga-run
tests/__init__.py